scimes/__init__.py
scimes/_astropy_init.py
scimes/conftest.py
scimes/old_spectral_embedding.py
scimes/orion2scimes.py
scimes/plotting.py
scimes/scimes.py
scimes/version.py
scimes-0.3.3.dist-info/METADATA
scimes-0.3.3.dist-info/WHEEL
scimes-0.3.3.dist-info/top_level.txt
scimes-0.3.3.dist-info/RECORD
