Metadata-Version: 2.1
Name: scimes
Version: 0.3.3
Summary: Spectral Clustering for Interstellar Molecular Emission Segmentation
Home-page: http://scimes.readthedocs.org/
Author: Dario Colombo, Erik Rosolowsky, Adam Ginsburg, Ana Duarte-Cabral, and Annie Hughes
Author-email: dario.colombo222@gmail.com
License: BSD
Classifier: Development Status :: 5 - Production/Stable
Classifier: Programming Language :: Python
Classifier: License :: OSI Approved :: MIT License
Classifier: Topic :: Scientific/Engineering :: Astronomy
Requires: astropy
Requires: numpy
Requires: matplotlib
Requires: astrodendro
Requires: sklearn
Provides: scimes
Requires-Dist: astropy
Requires-Dist: astrodendro
Requires-Dist: sklearn
